stem_feedback/__init__.py
stem_feedback/admin.py
stem_feedback/apps.py
stem_feedback/forms.py
stem_feedback/models.py
stem_feedback/tests.py
stem_feedback/urls.py
stem_feedback/utils.py
stem_feedback/views.py
stem_feedback/middleware/__init__.py
stem_feedback/middleware/current_user.py
stem_feedback/migrations/0001_initial.py
stem_feedback/migrations/0002_feedbackfiles.py
stem_feedback/migrations/0003_feedback.py
stem_feedback/migrations/0004_auto_20190111_0953.py
stem_feedback/migrations/__init__.py
stem_feedback/static/css/bootstrap.css
stem_feedback/static/css/style.css
stem_feedback/static/stem_feedback/js/upload_files.js
stem_feedback/templates/callback.html
stem_feedback/templates/email_complete.html
stem_feedback/templates/feedback.html
stem_feedback/templates/html-message.html
stem_feedback/templates/html-notification.html
stem_feedback/templates/moneyback.html
stem_feedback/templates/payment_notification.html
stem_feedback-0.5.12.dist-info/LICENSE
stem_feedback-0.5.12.dist-info/METADATA
stem_feedback-0.5.12.dist-info/WHEEL
stem_feedback-0.5.12.dist-info/top_level.txt
stem_feedback-0.5.12.dist-info/RECORD
