Metadata-Version: 2.1
Name: stem-feedback
Version: 0.5.12
Summary: Feedback package
Home-page: https://gitlab.stemsc.com/Belyak_Yuliya/feedback
Author: Belyak
Author-email: belyak.jul@gmail.com
License: UNKNOWN
Platform: UNKNOWN
Classifier: Programming Language :: Python :: 3
Classifier: License :: OSI Approved :: MIT License
Classifier: Operating System :: OS Independent
Requires-Dist: django (<2,>=1.11)
